recastatlas/__init__.py
recastatlas/_version.py
recastatlas/cli.py
recastatlas/config.py
recastatlas/exceptions.py
recastatlas/resultsextraction.py
recastatlas/testing.py
recastatlas/backends/__init__.py
recastatlas/backends/docker.py
recastatlas/backends/kubernetes.py
recastatlas/backends/local.py
recastatlas/backends/reana.py
recastatlas/data/expect_script.sh
recastatlas/data/getkrb_reana.sh
recastatlas/data/catalogue/atlas_atlas_conf_2018_041.yml
recastatlas/data/catalogue/busyboxtest.yml
recastatlas/data/catalogue/examples_checkmate1.yml
recastatlas/data/catalogue/examples_checkmate2.yml
recastatlas/data/catalogue/examples_rome.yml
recastatlas/data/templates/helloworld/recast.yml
recastatlas/data/templates/helloworld/specs/steps.yml
recastatlas/data/templates/helloworld/specs/workflow.yml
recastatlas/subcommands/__init__.py
recastatlas/subcommands/auth.py
recastatlas/subcommands/backends.py
recastatlas/subcommands/catalogue.py
recastatlas/subcommands/ci.py
recastatlas/subcommands/run.py
recastatlas/subcommands/software.py
recastatlas/subcommands/testing.py
recastatlas/test/.gitkeep
recast_atlas-0.4.2.dist-info/METADATA
recast_atlas-0.4.2.dist-info/WHEEL
recast_atlas-0.4.2.dist-info/entry_points.txt
recast_atlas-0.4.2.dist-info/licenses/LICENSE
recast_atlas-0.4.2.dist-info/RECORD
