Metadata-Version: 2.3
Name: recast_atlas
Version: 0.4.2
Summary: RECAST for ATLAS at the LHC
Project-URL: Documentation, https://github.com/recast-hep/recast-atlas
Project-URL: Homepage, https://github.com/recast-hep/recast-atlas
Project-URL: Issue Tracker, https://github.com/recast-hep/recast-atlas/issues
Project-URL: Releases, https://github.com/recast-hep/recast-atlas/releases
Project-URL: Source Code, https://github.com/recast-hep/recast-atlas
Author-email: Lukas Heinrich <lukas.heinrich@cern.ch>, Matthew Feickert <matthew.feickert@cern.ch>
Maintainer-email: Matthew Feickert <matthew.feickert@cern.ch>
License: Apache-2.0
License-File: LICENSE
Keywords: ATLAS,RECAST,analysis reuse,physics,reinterpretation
Classifier: Development Status :: 4 - Beta
Classifier: Intended Audience :: Science/Research
Classifier: License :: OSI Approved :: Apache Software License
Classifier: Programming Language :: Python :: 3
Classifier: Programming Language :: Python :: 3 :: Only
Classifier: Programming Language :: Python :: 3.8
Classifier: Programming Language :: Python :: 3.9
Classifier: Programming Language :: Python :: 3.10
Classifier: Programming Language :: Python :: 3.11
Classifier: Programming Language :: Python :: 3.12
Classifier: Programming Language :: Python :: Implementation :: CPython
Classifier: Topic :: Scientific/Engineering
Classifier: Topic :: Scientific/Engineering :: Physics
Requires-Python: >=3.8
Requires-Dist: click>=7.0
Requires-Dist: importlib-resources>=5.10; python_version < '3.9'
Requires-Dist: jsonschema>=3.0.0
Requires-Dist: pyyaml>=5.1
Requires-Dist: yadage-schemas>=0.10.7
Provides-Extra: all
Requires-Dist: adage>=0.10.1; extra == 'all'
Requires-Dist: kubernetes==9.0.0; extra == 'all'
Requires-Dist: packtivity>=0.14.23; extra == 'all'
Requires-Dist: pydot; extra == 'all'
Requires-Dist: pydotplus==2.0.2; extra == 'all'
Requires-Dist: pygraphviz; extra == 'all'
Requires-Dist: reana-client>=0.8.0; extra == 'all'
Requires-Dist: yadage>=0.20.1; extra == 'all'
Provides-Extra: develop
Requires-Dist: pre-commit; extra == 'develop'
Requires-Dist: pytest>=7.0.0; extra == 'develop'
Requires-Dist: ruff; extra == 'develop'
Provides-Extra: kubernetes
Requires-Dist: kubernetes==9.0.0; extra == 'kubernetes'
Provides-Extra: local
Requires-Dist: adage>=0.10.1; extra == 'local'
Requires-Dist: packtivity>=0.14.23; extra == 'local'
Requires-Dist: pydot; extra == 'local'
Requires-Dist: pydotplus==2.0.2; extra == 'local'
Requires-Dist: pygraphviz; extra == 'local'
Requires-Dist: yadage>=0.20.1; extra == 'local'
Provides-Extra: reana
Requires-Dist: reana-client>=0.8.0; extra == 'reana'
